edutech/__init__.py
edutech-4.0.1.dist-info/METADATA
edutech-4.0.1.dist-info/WHEEL
edutech-4.0.1.dist-info/top_level.txt
edutech-4.0.1.dist-info/RECORD
