Metadata-Version: 2.1
Name: edutech
Version: 4.0.1
Summary: this is my module
Home-page: UNKNOWN
Author: praveen kumar
License: UNKNOWN
Platform: UNKNOWN
